qurix/template/catalog/__init__.py
qurix/template/catalog/__version__.py
qurix/template/catalog/client.py
tests/__init__.py
tests/test_client.py
qurix_package_template-1.0.0.dist-info/METADATA
qurix_package_template-1.0.0.dist-info/WHEEL
qurix_package_template-1.0.0.dist-info/top_level.txt
qurix_package_template-1.0.0.dist-info/RECORD
