Metadata-Version: 2.1
Name: qurix-package-template
Version: 1.0.0
Summary: qurix Package Template for Python
Home-page: https://github.com/qurixtechnology/python-package-template
Author: qurix Technology
Keywords: python
Requires-Python: >=3.10, <4
Provides-Extra: dev
Requires-Dist: pytest (==7.3.1) ; extra == 'dev'
Requires-Dist: flake8 (==6.0.0) ; extra == 'dev'
Requires-Dist: pytest-flake8 (==1.1.1) ; extra == 'dev'
Requires-Dist: pytest-cov (==4.0.0) ; extra == 'dev'
Requires-Dist: wheel (==0.40.0) ; extra == 'dev'
Requires-Dist: twine (==4.0.2) ; extra == 'dev'
